graphene_mongodb/__init__.py
graphene_mongodb/model.py
graphene_mongodb/options.py
graphene_mongodb/schema.py
graphene_mongodb/fields/__init__.py
graphene_mongodb/fields/custom_fields.py
graphene_mongodb/fields/respective.py
graphene_mongodb/fields/special_fields.py
graphene_mongodb/mutation/__init__.py
graphene_mongodb/operators/__init__.py
graphene_mongodb/query/__init__.py
graphene_mongodb/query/utils.py
graphene_mongodb-1.0.1.dist-info/METADATA
graphene_mongodb-1.0.1.dist-info/RECORD
graphene_mongodb-1.0.1.dist-info/WHEEL
graphene_mongodb-1.0.1.dist-info/top_level.txt
