Metadata-Version: 2.1
Name: graphene-mongodb
Version: 1.0.1
Summary: GrapheneMongo is a library that integrates Graphene with MongoEngine
Home-page: https://github.com/joaovitorsilvestre/graphene-mongo
Author: João Vitor Silvestre
Author-email: joaovitorsilvestresousa@gmail.com
License: MIT
Download-URL: https://github.com/joaovitorsilvestre/graphene-mongo/archive/1.0.1.tar.gz
Keywords: graphene,graphql,mongo,mongodb,mongoDB,mongoengine,graphene-mongo,graphene-mongodb
Platform: UNKNOWN
Requires-Dist: aniso8601 (>=3.0.0)
Requires-Dist: appdirs (>=1.4.3)
Requires-Dist: graphene (>=2.1)
Requires-Dist: graphql-core (>=2.0)
Requires-Dist: graphql-relay (>=0.4.5)
Requires-Dist: iso8601 (>=0.1.12)
Requires-Dist: mongoengine (>=0.15.0)
Requires-Dist: promise (>=2.1)
Requires-Dist: pymongo (>=3.6.1)
Requires-Dist: pyparsing (>=2.2.0)
Requires-Dist: rx (>=1.6.1)
Requires-Dist: six (>=1.11.0)
Requires-Dist: typing (>=3.6.4)
